cdk_lambda_recaptcha_authorizer/__init__.py
cdk_lambda_recaptcha_authorizer/py.typed
cdk_lambda_recaptcha_authorizer/_jsii/__init__.py
cdk_lambda_recaptcha_authorizer/_jsii/cdk-lambda-recaptcha-authorizer@0.1.4.jsii.tgz
cdk_lambda_recaptcha_authorizer-0.1.4.dist-info/LICENSE
cdk_lambda_recaptcha_authorizer-0.1.4.dist-info/METADATA
cdk_lambda_recaptcha_authorizer-0.1.4.dist-info/WHEEL
cdk_lambda_recaptcha_authorizer-0.1.4.dist-info/top_level.txt
cdk_lambda_recaptcha_authorizer-0.1.4.dist-info/RECORD
