Metadata-Version: 2.1
Name: cdk-lambda-recaptcha-authorizer
Version: 0.1.4
Summary: Custom construct for AWS CDK that provides an easy way to integrate reCAPTCHA-based authorization with Amazon API Gateway.
Home-page: https://github.com/ilkerdagli/cdk-lambda-recaptcha-authorizer.git
Author: Ilker Dagli<daglilker@gmail.com>
License: MIT
Project-URL: Source, https://github.com/ilkerdagli/cdk-lambda-recaptcha-authorizer.git
Classifier: Intended Audience :: Developers
Classifier: Operating System :: OS Independent
Classifier: Programming Language :: JavaScript
Classifier: Programming Language :: Python :: 3 :: Only
Classifier: Programming Language :: Python :: 3.7
Classifier: Programming Language :: Python :: 3.8
Classifier: Programming Language :: Python :: 3.9
Classifier: Programming Language :: Python :: 3.10
Classifier: Programming Language :: Python :: 3.11
Classifier: Typing :: Typed
Classifier: Development Status :: 4 - Beta
Classifier: License :: OSI Approved
Requires-Python: ~=3.7
License-File: LICENSE
Requires-Dist: aws-cdk-lib <3.0.0,>=2.1.0
Requires-Dist: constructs <11.0.0,>=10.0.5
Requires-Dist: jsii <2.0.0,>=1.86.1
Requires-Dist: publication >=0.0.3
Requires-Dist: typeguard ~=2.13.3
